lich/__init__.py
lich/__main__.py
lich/cli.py
lich/version_check.py
lich/commands/__init__.py
lich/commands/adopt.py
lich/commands/backup.py
lich/commands/ci.py
lich/commands/ci_utils.py
lich/commands/deploy.py
lich/commands/dev.py
lich/commands/doctor.py
lich/commands/git.py
lich/commands/init.py
lich/commands/lint.py
lich/commands/make.py
lich/commands/middleware.py
lich/commands/migration.py
lich/commands/production_ready.py
lich/commands/routes.py
lich/commands/secret.py
lich/commands/security.py
lich/commands/seed.py
lich/commands/setup.py
lich/commands/shell.py
lich/commands/test.py
lich/commands/upgrade.py
lich/commands/version.py
lich/mcp/__init__.py
lich/mcp/server.py
lich/mcp/tools/__init__.py
lich/mcp/tools/ci.py
lich/mcp/tools/dev.py
lich/mcp/tools/git.py
lich/mcp/tools/make.py
lich/mcp/tools/migration.py
lich/mcp/tools/mw.py
lich/mcp/tools/ops.py
lich/mcp/tools/production.py
lich/mcp/tools/project.py
lich/mcp/tools/qa.py
lich/mcp/tools/routes.py
lich/mcp/tools/secret.py
lich/mcp/tools/seed.py
lich/mcp/tools/utility.py
lich-1.12.15.dist-info/METADATA
lich-1.12.15.dist-info/WHEEL
lich-1.12.15.dist-info/entry_points.txt
lich-1.12.15.dist-info/top_level.txt
lich-1.12.15.dist-info/RECORD
