Metadata-Version: 2.4
Name: lich
Version: 1.12.15
Summary: AI-Ready Full-Stack Project Generator
Author-email: Babak <babak@example.com>
License: MIT
Project-URL: Homepage, https://dotech-fi.github.io/lich/
Project-URL: Documentation, https://dotech-fi.github.io/lich/
Project-URL: Repository, https://github.com/DoTech-fi/lich.git
Project-URL: Issues, https://github.com/DoTech-fi/lich/issues
Project-URL: Changelog, https://github.com/DoTech-fi/lich/blob/main/CHANGELOG.md
Keywords: cookiecutter,project-generator,fastapi,nextjs,cli
Classifier: Development Status :: 4 - Beta
Classifier: Environment :: Console
Classifier: Intended Audience :: Developers
Classifier: License :: OSI Approved :: MIT License
Classifier: Programming Language :: Python :: 3
Classifier: Programming Language :: Python :: 3.10
Classifier: Programming Language :: Python :: 3.11
Classifier: Programming Language :: Python :: 3.12
Requires-Python: >=3.10
Requires-Dist: typer>=0.9.0
Requires-Dist: cookiecutter>=2.5.0
Requires-Dist: rich>=13.0.0
Requires-Dist: pyyaml>=6.0
Requires-Dist: requests>=2.28.0
Requires-Dist: mcp>=0.1.0
Provides-Extra: dev
Requires-Dist: pytest>=8.0.0; extra == "dev"
Requires-Dist: pytest-asyncio>=0.23.0; extra == "dev"
Requires-Dist: pytest-mock>=3.14.0; extra == "dev"
